assets/__init__.py
modules/Information.py
modules/__init__.py
modules/config.py
modules/file_option.py
modules/fimport.py
modules/load_files.py
modules/showSIM.py
modules/troubleshooting.py
templates/__init__.py
Eliteproject_SBANDI-2025.2.27.dist-info/METADATA
Eliteproject_SBANDI-2025.2.27.dist-info/WHEEL
Eliteproject_SBANDI-2025.2.27.dist-info/top_level.txt
Eliteproject_SBANDI-2025.2.27.dist-info/RECORD
