Metadata-Version: 2.2
Name: Eliteproject-SBANDI
Version: 2025.2.27
Summary: OEC ELITE LOG PARSER
Home-page: https://github.com/users/Egorroico/projects/1/views/1
Author: Stefano Bandini
Author-email: stefano.bandini@email.it
Classifier: Programming Language :: Python :: 3
Classifier: License :: OSI Approved :: MIT License
Classifier: Operating System :: OS Independent
Requires-Python: >=3.7
Dynamic: author
Dynamic: author-email
Dynamic: classifier
Dynamic: description
Dynamic: description-content-type
Dynamic: home-page
Dynamic: requires-python
Dynamic: summary
